lial_user/__init__.py
lial_user-1.2.4.dist-info/METADATA
lial_user-1.2.4.dist-info/WHEEL
lial_user-1.2.4.dist-info/top_level.txt
lial_user-1.2.4.dist-info/RECORD
