Metadata-Version: 2.2
Name: lial_user
Version: 1.2.4
Summary: Une librairie de fonctions pour intéragir avec la base de données des utilisateurs du LIAL
Author: SIGIER Luc
Author-email: l.sigier@lialrioz.fr
Classifier: Programming Language :: Python :: 3
Classifier: Operating System :: OS Independent
Requires-Python: >=3.6
Requires-Dist: pyodbc
Requires-Dist: mysql-connector-python
Dynamic: author
Dynamic: author-email
Dynamic: classifier
Dynamic: requires-dist
Dynamic: requires-python
Dynamic: summary
